[
  {
    "id": "food_001",
    "title": "人均50吃到撑！这家川菜太绝了",
    "content": "终于找到一家好吃不贵的川菜馆！！\n\n📍地址：xx路xx号（地铁x号线x站）\n💰人均：50元\n⏰营业时间：11:00-22:00\n\n必点菜品：\n1. 水煮牛肉 - 麻辣鲜香，牛肉超嫩\n2. 酸菜鱼 - 酸爽开胃，鱼片很厚\n3. 干煸四季豆 - 下饭神器\n4. 蒜泥白肉 - 蒜香浓郁\n\n避雷：\n- 回锅肉偏咸，不太推荐\n\n环境一般，但味道真的绝！适合朋友聚餐～\n\n你们还有什么平价川菜推荐？",
    "category": "food",
    "subTopic": "restaurant",
    "quality": "excellent",
    "keyFeatures": "信息完整（地址、人均、时间），必点和避雷都有",
    "metrics": {"likes": 3256, "collects": 1432},
    "tags": ["#美食探店", "#川菜", "#平价美食", "#聚餐推荐"]
  },
  {
    "id": "food_002",
    "title": "空气炸锅神仙食谱｜懒人必备",
    "content": "空气炸锅真的是懒人福音！\n\n【炸鸡翅】\n温度：200°C\n时间：20分钟\n调料：盐、黑胡椒、蒜粉\n翻面一次，外酥里嫩！\n\n【烤红薯】\n温度：200°C\n时间：40分钟\n不用加任何东西！\n\n【炸薯条】\n温度：180°C\n时间：15分钟\n喷点油更酥脆\n\n【烤蛋挞】\n温度：180°C\n时间：12分钟\n买现成蛋挞皮就行\n\n小tips：\n- 食材不要放太满\n- 中途记得翻面\n- 第一次用先空烧5分钟\n\n你们还有什么好做的食谱？",
    "category": "food",
    "subTopic": "air-fryer",
    "quality": "excellent",
    "keyFeatures": "温度时间精确，步骤简单易操作",
    "metrics": {"likes": 9876, "collects": 5432},
    "tags": ["#空气炸锅", "#懒人食谱", "#宅家美食", "#厨房小白"]
  },
  {
    "id": "food_003",
    "title": "一人食｜独居女生的快手晚餐",
    "content": "独居第3年，终于学会好好吃饭了\n\n今日晚餐：番茄鸡蛋盖饭\n\n食材：\n番茄1个、鸡蛋2个、米饭1碗\n\n步骤：\n1. 番茄切块，鸡蛋打散\n2. 热油炒鸡蛋，盛出备用\n3. 番茄炒出汁，加点糖\n4. 倒入鸡蛋，加盐调味\n5. 浇在米饭上，完成！\n\n用时：10分钟\n成本：不到5块钱\n\n一个人也要好好吃饭\n对自己好一点～\n\n独居的姐妹们都在吃什么？",
    "category": "food",
    "subTopic": "solo-meal",
    "quality": "good",
    "keyFeatures": "步骤简单，成本时间都标注，情感共鸣",
    "metrics": {"likes": 4532, "collects": 2341},
    "tags": ["#一人食", "#独居生活", "#快手菜", "#简单料理"]
  }
]
